onionvalidator/__init__.py
onionvalidator/core.py
onionvalidator-1.5.9.dist-info/METADATA
onionvalidator-1.5.9.dist-info/WHEEL
onionvalidator-1.5.9.dist-info/entry_points.txt
onionvalidator-1.5.9.dist-info/top_level.txt
onionvalidator-1.5.9.dist-info/RECORD
