Metadata-Version: 2.4
Name: onionvalidator
Version: 1.5.9
Summary: Validate .onion addresses using public darknet sources
Author-email: Zero <zero@example.com>
License: MIT
Requires-Python: >=3.7
Requires-Dist: requests
Requires-Dist: beautifulsoup4
